CONTRIBUTING.md
MANIFEST.in
README.rst
setup.cfg
setup.py
docs/HISTORY.txt
docs/INSTALL.txt
docs/LICENSE.GPL
docs/LICENSE.txt
eea/__init__.py
eea.annotator.egg-info/PKG-INFO
eea.annotator.egg-info/SOURCES.txt
eea.annotator.egg-info/dependency_links.txt
eea.annotator.egg-info/entry_points.txt
eea.annotator.egg-info/namespace_packages.txt
eea.annotator.egg-info/not-zip-safe
eea.annotator.egg-info/requires.txt
eea.annotator.egg-info/top_level.txt
eea/annotator/README.txt
eea/annotator/__init__.py
eea/annotator/config.py
eea/annotator/configure.zcml
eea/annotator/interfaces.py
eea/annotator/permissions.zcml
eea/annotator/profiles.zcml
eea/annotator/version.txt
eea/annotator/Extensions/install.py
eea/annotator/browser/__init__.py
eea/annotator/browser/configure.zcml
eea/annotator/browser/interfaces.py
eea/annotator/browser/app/__init__.py
eea/annotator/browser/app/moderate.py
eea/annotator/browser/app/subscription.py
eea/annotator/browser/app/traverse.py
eea/annotator/browser/app/view.py
eea/annotator/browser/app/viewlet.py
eea/annotator/browser/compiled/eea.annotator-compiled.css
eea/annotator/browser/compiled/eea.annotator-compiled.css.map
eea/annotator/browser/compiled/eea.annotator-compiled.js
eea/annotator/browser/compiled/eea.annotator-compiled.js.map
eea/annotator/browser/css/edit.css
eea/annotator/browser/css/view.css
eea/annotator/browser/img/icon.png
eea/annotator/browser/js/eea.annotator-view-compiled.js
eea/annotator/browser/js/view.js
eea/annotator/browser/zpt/moderate-comment.pt
eea/annotator/browser/zpt/moderate-comments.pt
eea/annotator/browser/zpt/viewlet.pt
eea/annotator/cache/__init__.py
eea/annotator/cache/cache.py
eea/annotator/cache/configure.zcml
eea/annotator/cache/nocache.py
eea/annotator/controlpanel/__init__.py
eea/annotator/controlpanel/configure.zcml
eea/annotator/controlpanel/interfaces.py
eea/annotator/controlpanel/settings.py
eea/annotator/events/__init__.py
eea/annotator/events/comment.py
eea/annotator/events/configure.zcml
eea/annotator/events/interfaces.py
eea/annotator/locales/eea.pot
eea/annotator/locales/update.sh
eea/annotator/locales/bg/LC_MESSAGES/eea.po
eea/annotator/locales/cs/LC_MESSAGES/eea.po
eea/annotator/locales/da/LC_MESSAGES/eea.po
eea/annotator/locales/de/LC_MESSAGES/eea.po
eea/annotator/locales/el/LC_MESSAGES/eea.po
